MK8D/__init__.py
MK8D/_version.py
MK8D/auxiliary.py
MK8D/color.py
MK8D/constants.py
MK8D/dataTransform.py
MK8D/xmlParse.py
MK8D-0.0.6.data/scripts/MK8D_run2csv
MK8D-0.0.6.data/scripts/MK8D_trk2csv
MK8D-0.0.6.dist-info/LICENSE
MK8D-0.0.6.dist-info/METADATA
MK8D-0.0.6.dist-info/WHEEL
MK8D-0.0.6.dist-info/top_level.txt
MK8D-0.0.6.dist-info/RECORD
