Metadata-Version: 2.1
Name: MK8D
Version: 0.0.6
Summary: Mario Kart 8 Deluxe livesplit analyzer
Home-page: https://github.com/Chipdelmal/MK8D
Author: chipdelmal
Author-email: chipdelmal@gmail.com
License: UNKNOWN
Platform: UNKNOWN
Classifier: Programming Language :: Python :: 3
Classifier: License :: OSI Approved :: Apache Software License
Classifier: Operating System :: OS Independent
Requires-Python: >=3.8
Requires-Dist: matplotlib (>=3.3.2)
Requires-Dist: xmltodict (>=0.12.0)
Requires-Dist: pandas (>=1.1.4)
Requires-Dist: numpy (>=1.19.4)
Requires-Dist: plotly (>=4.13.0)
Requires-Dist: plotly-express (>=0.4.1)
Requires-Dist: colour (>=0.1.5)
